odoo10_addon_component-10.0.1.1.1-nspkg.pth
odoo/addons/component/README.rst
odoo/addons/component/__init__.py
odoo/addons/component/__manifest__.py
odoo/addons/component/builder.py
odoo/addons/component/core.py
odoo/addons/component/exception.py
odoo/addons/component/components/__init__.py
odoo/addons/component/components/base.py
odoo/addons/component/i18n/am.po
odoo/addons/component/i18n/ca.po
odoo/addons/component/i18n/component.pot
odoo/addons/component/i18n/de.po
odoo/addons/component/i18n/el_GR.po
odoo/addons/component/i18n/es.po
odoo/addons/component/i18n/es_ES.po
odoo/addons/component/i18n/fi.po
odoo/addons/component/i18n/fr.po
odoo/addons/component/i18n/gl.po
odoo/addons/component/i18n/it.po
odoo/addons/component/i18n/pt.po
odoo/addons/component/i18n/pt_BR.po
odoo/addons/component/i18n/pt_PT.po
odoo/addons/component/i18n/sl.po
odoo/addons/component/i18n/tr.po
odoo/addons/component/models/__init__.py
odoo/addons/component/models/collection.py
odoo/addons/component/static/description/icon.png
odoo/addons/component/tests/__init__.py
odoo/addons/component/tests/common.py
odoo/addons/component/tests/test_build_component.py
odoo/addons/component/tests/test_component.py
odoo/addons/component/tests/test_lookup.py
odoo/addons/component/tests/test_work_on.py
odoo10_addon_component-10.0.1.1.1.dist-info/METADATA
odoo10_addon_component-10.0.1.1.1.dist-info/WHEEL
odoo10_addon_component-10.0.1.1.1.dist-info/namespace_packages.txt
odoo10_addon_component-10.0.1.1.1.dist-info/top_level.txt
odoo10_addon_component-10.0.1.1.1.dist-info/RECORD
